LICENSE
MANIFEST.in
README.rst
setup.cfg
setup.py
djangocms_owl/__init__.py
djangocms_owl/cms_plugins.py
djangocms_owl/conf.py
djangocms_owl/models.py
djangocms_owl.egg-info/PKG-INFO
djangocms_owl.egg-info/SOURCES.txt
djangocms_owl.egg-info/dependency_links.txt
djangocms_owl.egg-info/not-zip-safe
djangocms_owl.egg-info/requires.txt
djangocms_owl.egg-info/top_level.txt
djangocms_owl/migrations/0001_initial.py
djangocms_owl/migrations/0002_owlcarousel_extra_options.py
djangocms_owl/migrations/__init__.py
djangocms_owl/south_migrations/0001_initial.py
djangocms_owl/south_migrations/0002_auto__add_field_owlcarousel_extra_options.py
djangocms_owl/south_migrations/__init__.py
djangocms_owl/static/djangocms_owl/bower_components/jquery/dist/jquery.js
djangocms_owl/static/djangocms_owl/bower_components/jquery/dist/jquery.min.js
djangocms_owl/static/djangocms_owl/bower_components/jquery/src/ajax.js
djangocms_owl/static/djangocms_owl/bower_components/jquery/src/attributes.js
djangocms_owl/static/djangocms_owl/bower_components/jquery/src/callbacks.js
djangocms_owl/static/djangocms_owl/bower_components/jquery/src/core.js
djangocms_owl/static/djangocms_owl/bower_components/jquery/src/css.js
djangocms_owl/static/djangocms_owl/bower_components/jquery/src/data.js
djangocms_owl/static/djangocms_owl/bower_components/jquery/src/deferred.js
djangocms_owl/static/djangocms_owl/bower_components/jquery/src/deprecated.js
djangocms_owl/static/djangocms_owl/bower_components/jquery/src/dimensions.js
djangocms_owl/static/djangocms_owl/bower_components/jquery/src/effects.js
djangocms_owl/static/djangocms_owl/bower_components/jquery/src/event.js
djangocms_owl/static/djangocms_owl/bower_components/jquery/src/intro.js
djangocms_owl/static/djangocms_owl/bower_components/jquery/src/jquery.js
djangocms_owl/static/djangocms_owl/bower_components/jquery/src/manipulation.js
djangocms_owl/static/djangocms_owl/bower_components/jquery/src/offset.js
djangocms_owl/static/djangocms_owl/bower_components/jquery/src/outro.js
djangocms_owl/static/djangocms_owl/bower_components/jquery/src/queue.js
djangocms_owl/static/djangocms_owl/bower_components/jquery/src/selector-native.js
